seleniumabsxy/README.MD
seleniumabsxy/__init__.py
seleniumabsxy/requirements.txt
seleniumabsxy/thirdparty.json
seleniumabsxy-0.10.dist-info/LICENSE.rst
seleniumabsxy-0.10.dist-info/METADATA
seleniumabsxy-0.10.dist-info/WHEEL
seleniumabsxy-0.10.dist-info/top_level.txt
seleniumabsxy-0.10.dist-info/RECORD
