Metadata-Version: 2.1
Name: seleniumabsxy
Version: 0.10
Summary: Clicks on Selenium webelements at a certain screen position (x,y)
Home-page: https://github.com/hansalemaos/seleniumabsxy
Author: Johannes Fischer
Author-email: aulasparticularesdealemaosp@gmail.com
License: MIT
Keywords: selenium,coordinates
Classifier: Development Status :: 4 - Beta
Classifier: Programming Language :: Python :: 3 :: Only
Classifier: Programming Language :: Python :: 3.10
Classifier: Topic :: Software Development :: Libraries :: Python Modules
Classifier: Topic :: Utilities
License-File: LICENSE.rst
Requires-Dist: a-selenium-click-on-coords
Requires-Dist: ctypes-window-info
Requires-Dist: keyboard
Requires-Dist: mousekey
